yahoo_oauth_fantasy/__init__.py
yahoo_oauth_fantasy/logger.py
yahoo_oauth_fantasy/oauth.py
yahoo_oauth_fantasy/utils.py
yahoo_oauth_fantasy-0.1.0.dist-info/METADATA
yahoo_oauth_fantasy-0.1.0.dist-info/WHEEL
yahoo_oauth_fantasy-0.1.0.dist-info/top_level.txt
yahoo_oauth_fantasy-0.1.0.dist-info/RECORD
