Metadata-Version: 2.1
Name: yahoo-oauth-fantasy
Version: 0.1.0
Summary: Python Yahoo OAuth Library. Supports OAuth1 and OAuth2. Gets data from function variables or file
Home-page: https://github.com/runner15/yahoo_oauth_fantasy
Author: Runner15
License: MIT
Keywords: yahoo,oauth,oauth1,oauth2
Platform: UNKNOWN
Requires-Dist: pyaml
Requires-Dist: rauth
